key_func/__init__.py
key_func/key_func.py
key_func-0.0.1.dist-info/METADATA
key_func-0.0.1.dist-info/WHEEL
key_func-0.0.1.dist-info/top_level.txt
key_func-0.0.1.dist-info/RECORD
